seaoligo_common/__init__.py
seaoligo_common/config.py
seaoligo_common/app/__init__.py
seaoligo_common/lib/__init__.py
seaoligo_common/lib/types.py
seaoligo_common/lib/util_sqlalchemy.py
seaoligo_common/lib/util_strawberry.py
seaoligo_common-2.0.13.dist-info/LICENSE
seaoligo_common-2.0.13.dist-info/METADATA
seaoligo_common-2.0.13.dist-info/WHEEL
seaoligo_common-2.0.13.dist-info/top_level.txt
seaoligo_common-2.0.13.dist-info/RECORD
