Metadata-Version: 2.1
Name: seaoligo-common
Version: 2.0.13
Summary: SEA Web Services common python packages
Home-page: https://github.com/sea-biopharma/seaoligo-common
Author: SEA Biopharma
Author-email: sea.biopharma@gmail.com
License: UNKNOWN
Platform: UNKNOWN
Requires-Python: >=3.8
Requires-Dist: flask-sqlalchemy (>=2.4.4)
Requires-Dist: flask (>=1.1.2)
Requires-Dist: strawberry-graphql (>=0.45.3)
